lit_mlflow/__about__.py
lit_mlflow/__init__.py
lit_mlflow/callback.py
lit_mlflow/cli.py
lit_mlflow/logger.py
lit_mlflow/py.typed
lit_mlflow/utils/dbx.py
lit_mlflow-0.1.2.dist-info/METADATA
lit_mlflow-0.1.2.dist-info/WHEEL
lit_mlflow-0.1.2.dist-info/entry_points.txt
lit_mlflow-0.1.2.dist-info/licenses/LICENSE
lit_mlflow-0.1.2.dist-info/RECORD
