Metadata-Version: 2.4
Name: lit-mlflow
Version: 0.1.2
Summary: An improved Lightning mlflow logger
License: MIT
License-File: LICENSE
Keywords: lit-mlflow
Author: twsl
Author-email: 45483159+twsl@users.noreply.github.com
Requires-Python: >=3.11
Classifier: License :: OSI Approved :: MIT License
Classifier: Programming Language :: Python :: 3
Classifier: Programming Language :: Python :: 3.11
Classifier: Programming Language :: Python :: 3.12
Classifier: Programming Language :: Python :: 3.13
Classifier: Programming Language :: Python :: 3.14
Requires-Dist: databricks-cli (>=0.18.0,<0.19.0)
Requires-Dist: lightning (>=2.6.0,<3.0.0)
Requires-Dist: mlflow (>=3.6.0,<4.0.0)
Project-URL: Documentation, https://twsl.github.io/lit-mlflow/
Project-URL: Homepage, https://twsl.github.io/lit-mlflow/
Project-URL: Repository, https://github.com/twsl/lit-mlflow
